iiiflow/__init__.py
iiiflow/conversions.py
iiiflow/hocr_indexer.py
iiiflow/index_collection.py
iiiflow/manifest.py
iiiflow/metadata.py
iiiflow/pdf.py
iiiflow/ptif.py
iiiflow/tesseract.py
iiiflow/thumbnail.py
iiiflow/transcribe.py
iiiflow/update_manifests.py
iiiflow/utils.py
iiiflow-0.8.2.dist-info/licenses/LICENSE
iiiflow-0.8.2.dist-info/METADATA
iiiflow-0.8.2.dist-info/WHEEL
iiiflow-0.8.2.dist-info/entry_points.txt
iiiflow-0.8.2.dist-info/top_level.txt
iiiflow-0.8.2.dist-info/RECORD
