Metadata-Version: 2.4
Name: iiiflow
Version: 0.8.2
Summary: An IIIF pipeline tool using the Digital Object Discovery Storage Specification.
Home-page: https://github.com/UAlbanyArchives/arclight_integration_project
Author: Gregory Wiedeman
Author-email: gwiedeman@albany.edu
Classifier: Programming Language :: Python :: 3
Classifier: License :: OSI Approved :: MIT License
Classifier: Operating System :: OS Independent
Requires-Python: >=3.8
License-File: LICENSE
Requires-Dist: PyYAML==6.0.2
Requires-Dist: pypdf==3.14.0
Requires-Dist: requests==2.32.3
Requires-Dist: pycryptodome==3.15.0
Requires-Dist: iiif-prezi3==2.0.1
Requires-Dist: openai-whisper==20240930
Requires-Dist: mutagen==1.47.0
Requires-Dist: ffmpeg-python==0.2.0
Requires-Dist: pyvips==2.2.3
Requires-Dist: pandas==2.2.3
Requires-Dist: beautifulsoup4==4.12.3
Requires-Dist: lxml>=5.3.0
Requires-Dist: pysolr==3.10.0
Requires-Dist: pytest
Dynamic: author
Dynamic: author-email
Dynamic: classifier
Dynamic: description-content-type
Dynamic: home-page
Dynamic: license-file
Dynamic: requires-dist
Dynamic: requires-python
Dynamic: summary
